glokov
