Metadata-Version: 1.0
Name: glokov
Version: 0.1.3
Summary: A text generation library
Home-page: http://github.com/MatthewScholefield/glokov
Author: Matthew Scholefield
Author-email: matthew331199@gmail.com
License: MIT
Platform: UNKNOWN
